wrfo/__init__.py
wrfo/diversity.py
wrfo/metrics.py
wrfo/objective.py
wrfo/optimizer.py
wrfo-1.0.2.dist-info/licenses/LICENSE
wrfo-1.0.2.dist-info/METADATA
wrfo-1.0.2.dist-info/WHEEL
wrfo-1.0.2.dist-info/top_level.txt
wrfo-1.0.2.dist-info/RECORD
