Metadata-Version: 2.4
Name: wrfo
Version: 1.0.2
Summary: Tree Weighting, Accuracy and Diversity-Preserving Pruning for Random Forests
Home-page: https://github.com/wajdidhifli/WRFO
Author: Wajdi DHIFLI
Author-email: wajdidhifli@gmail.com
Project-URL: Homepage, https://github.com/wajdidhifli/WRFO
Project-URL: Source, https://github.com/wajdidhifli/WRFO
Project-URL: Bug Reports, https://github.com/wajdidhifli/WRFO/issues
Classifier: Development Status :: 4 - Beta
Classifier: Intended Audience :: Science/Research
Classifier: Topic :: Scientific/Engineering :: Artificial Intelligence
Classifier: License :: OSI Approved :: MIT License
Classifier: Programming Language :: Python :: 3
Classifier: Programming Language :: Python :: 3.7
Classifier: Programming Language :: Python :: 3.8
Classifier: Programming Language :: Python :: 3.9
Classifier: Programming Language :: Python :: 3.10
Requires-Python: >=3.7
License-File: LICENSE
Requires-Dist: numpy>=1.20.0
Requires-Dist: pandas>=1.3.0
Requires-Dist: scikit-learn>=1.0.0
Requires-Dist: pyswarm>=0.6
Requires-Dist: scipy>=1.7.0
Requires-Dist: joblib>=1.0.0
Requires-Dist: tqdm>=4.62.0
Provides-Extra: dev
Requires-Dist: pytest>=6.0; extra == "dev"
Requires-Dist: pytest-cov>=2.0; extra == "dev"
Requires-Dist: black>=21.0; extra == "dev"
Requires-Dist: flake8>=3.9; extra == "dev"
Dynamic: author
Dynamic: author-email
Dynamic: classifier
Dynamic: description
Dynamic: description-content-type
Dynamic: home-page
Dynamic: license-file
Dynamic: project-url
Dynamic: provides-extra
Dynamic: requires-dist
Dynamic: requires-python
Dynamic: summary
